gradient_free_optimizers/__init__.py
gradient_free_optimizers/_init_utils.py
gradient_free_optimizers/_memory.py
gradient_free_optimizers/_objective_adapter.py
gradient_free_optimizers/_print_info.py
gradient_free_optimizers/_progress_bar.py
gradient_free_optimizers/_result.py
gradient_free_optimizers/_results_manager.py
gradient_free_optimizers/_search_statistics.py
gradient_free_optimizers/_stop_run.py
gradient_free_optimizers/_stopping_conditions.py
gradient_free_optimizers/_times_tracker.py
gradient_free_optimizers/search.py
gradient_free_optimizers/_array_backend/__init__.py
gradient_free_optimizers/_array_backend/_numpy.py
gradient_free_optimizers/_array_backend/_pure.py
gradient_free_optimizers/_estimators/__init__.py
gradient_free_optimizers/_estimators/_decision_tree_regressor.py
gradient_free_optimizers/_estimators/_extra_trees_regressor.py
gradient_free_optimizers/_estimators/_gaussian_process_regressor.py
gradient_free_optimizers/_estimators/_gradient_boosting_regressor.py
gradient_free_optimizers/_estimators/_kernel_density_estimator.py
gradient_free_optimizers/_estimators/_random_forest_regressor.py
gradient_free_optimizers/_math_backend/__init__.py
gradient_free_optimizers/_math_backend/_pure.py
gradient_free_optimizers/_math_backend/_scipy.py
gradient_free_optimizers/_objective_functions/__init__.py
gradient_free_optimizers/_objective_functions/_ackley_function.py
gradient_free_optimizers/_objective_functions/_base_function.py
gradient_free_optimizers/_objective_functions/_sphere_function.py
gradient_free_optimizers/optimizer_search/__init__.py
gradient_free_optimizers/optimizer_search/bayesian_optimization.py
gradient_free_optimizers/optimizer_search/differential_evolution.py
gradient_free_optimizers/optimizer_search/direct_algorithm.py
gradient_free_optimizers/optimizer_search/downhill_simplex.py
gradient_free_optimizers/optimizer_search/ensemble_optimizer.py
gradient_free_optimizers/optimizer_search/evolution_strategy.py
gradient_free_optimizers-1.9.0.dist-info/METADATA
gradient_free_optimizers-1.9.0.dist-info/WHEEL
gradient_free_optimizers-1.9.0.dist-info/top_level.txt
gradient_free_optimizers-1.9.0.dist-info/RECORD
