Metadata-Version: 2.4
Name: gradient-free-optimizers
Version: 1.9.0
Summary: Simple and reliable optimization with local, global, population-based and sequential techniques in numerical discrete search spaces.
Author-email: Simon Blanke <simon.blanke@yahoo.com>
Maintainer-email: Simon Blanke <simon.blanke@yahoo.com>
Project-URL: Homepage, https://github.com/SimonBlanke/Gradient-Free-Optimizers
Project-URL: Bug Reports, https://github.com/SimonBlanke/Gradient-Free-Optimizers/issues
Project-URL: Source, https://github.com/SimonBlanke/Gradient-Free-Optimizers/
Keywords: optimization,hyperparameter-optimization,hyperparameter-tuning,machine-learning,meta-heuristic,bayesian-optimization,genetic-algorithm,particle-swarm,evolution-strategy,hill-climbing,simulated-annealing,gradient-free,black-box-optimization,numerical-optimization,automl,search-algorithms,optimization-algorithms,data-science,visualization
Classifier: Development Status :: 5 - Production/Stable
Classifier: Programming Language :: Python :: 3
Classifier: Programming Language :: Python :: 3.10
Classifier: Programming Language :: Python :: 3.11
Classifier: Programming Language :: Python :: 3.12
Classifier: Programming Language :: Python :: 3.13
Classifier: Programming Language :: Python :: 3.14
Classifier: License :: OSI Approved :: MIT License
Classifier: Operating System :: OS Independent
Classifier: Natural Language :: English
Classifier: Topic :: Scientific/Engineering
Classifier: Topic :: Scientific/Engineering :: Artificial Intelligence
Classifier: Topic :: Scientific/Engineering :: Information Analysis
Classifier: Topic :: Scientific/Engineering :: Mathematics
Classifier: Topic :: Software Development :: Libraries
Classifier: Topic :: Software Development :: Libraries :: Python Modules
Classifier: Intended Audience :: Developers
Classifier: Intended Audience :: Education
Classifier: Intended Audience :: Information Technology
Classifier: Intended Audience :: Science/Research
Requires-Python: >=3.10
Requires-Dist: numpy<3.0.0,>=1.18.1
Requires-Dist: pandas<3.0.0
Provides-Extra: progress
Requires-Dist: tqdm<5.0.0,>=4.48.0; extra == "progress"
Provides-Extra: sklearn
Requires-Dist: scikit-learn!=0.23.*,>=0.21; extra == "sklearn"
Provides-Extra: full
Requires-Dist: scipy<2.0.0; extra == "full"
Requires-Dist: scikit-learn!=0.23.*,>=0.21; extra == "full"
Requires-Dist: tqdm<5.0.0,>=4.48.0; extra == "full"
Provides-Extra: build
Requires-Dist: setuptools; extra == "build"
Requires-Dist: build; extra == "build"
Requires-Dist: wheel; extra == "build"
Provides-Extra: test
Requires-Dist: pytest==9.0.2; extra == "test"
Requires-Dist: flake8; extra == "test"
Requires-Dist: pytest-cov; extra == "test"
Requires-Dist: surfaces; extra == "test"
Requires-Dist: scikit-learn!=0.23.*,>=0.21; extra == "test"
